odoo/addons/account_consolidation_oca/README.rst
odoo/addons/account_consolidation_oca/__init__.py
odoo/addons/account_consolidation_oca/__manifest__.py
odoo/addons/account_consolidation_oca/hooks.py
odoo/addons/account_consolidation_oca/demo/company_a_demo.xml
odoo/addons/account_consolidation_oca/demo/company_b_demo.xml
odoo/addons/account_consolidation_oca/demo/company_demo.xml
odoo/addons/account_consolidation_oca/demo/consolidation_demo.xml
odoo/addons/account_consolidation_oca/demo/currency_demo.xml
odoo/addons/account_consolidation_oca/i18n/account_consolidation_oca.pot
odoo/addons/account_consolidation_oca/i18n/es.po
odoo/addons/account_consolidation_oca/i18n/hr.po
odoo/addons/account_consolidation_oca/i18n/it.po
odoo/addons/account_consolidation_oca/i18n/pt.po
odoo/addons/account_consolidation_oca/i18n/pt_BR.po
odoo/addons/account_consolidation_oca/models/__init__.py
odoo/addons/account_consolidation_oca/models/account.py
odoo/addons/account_consolidation_oca/models/account_move.py
odoo/addons/account_consolidation_oca/models/company.py
odoo/addons/account_consolidation_oca/models/consolidation_profile.py
odoo/addons/account_consolidation_oca/models/res_config_settings.py
odoo/addons/account_consolidation_oca/readme/CONFIGURE.rst
odoo/addons/account_consolidation_oca/readme/DESCRIPTION.rst
odoo/addons/account_consolidation_oca/readme/ROADMAP.rst
odoo/addons/account_consolidation_oca/readme/USAGE.rst
odoo/addons/account_consolidation_oca/security/account_consolidation_security.xml
odoo/addons/account_consolidation_oca/security/ir.model.access.csv
odoo/addons/account_consolidation_oca/security/res_groups.xml
odoo/addons/account_consolidation_oca/static/description/icon.png
odoo/addons/account_consolidation_oca/static/description/index.html
odoo/addons/account_consolidation_oca/tests/__init__.py
odoo/addons/account_consolidation_oca/tests/test_account_company_rules.py
odoo/addons/account_consolidation_oca/tests/test_account_consolidation.py
odoo14_addon_account_consolidation_oca-14.0.1.0.1.dev5.dist-info/METADATA
odoo14_addon_account_consolidation_oca-14.0.1.0.1.dev5.dist-info/WHEEL
odoo14_addon_account_consolidation_oca-14.0.1.0.1.dev5.dist-info/top_level.txt
odoo14_addon_account_consolidation_oca-14.0.1.0.1.dev5.dist-info/RECORD
